brk_rpa_utils/__about__.py
brk_rpa_utils/__init__.py
brk_rpa_utils/login.py
brk_rpa_utils-0.0.1.dist-info/METADATA
brk_rpa_utils-0.0.1.dist-info/WHEEL
brk_rpa_utils-0.0.1.dist-info/licenses/LICENSE.txt
brk_rpa_utils-0.0.1.dist-info/RECORD
