Metadata-Version: 2.1
Name: brk-rpa-utils
Version: 0.0.1
Project-URL: Documentation, https://github.com/dzgreen/brk-rpa-utils#readme
Project-URL: Issues, https://github.com/dzgreen/brk-rpa-utils/issues
Project-URL: Source, https://github.com/dzgreen/brk-rpa-utils
Author-email: Dominik Zdyb Lillemaehlum <Dominik.Zdyb.Lillemaehlum@brk.dk>
License-Expression: MIT
License-File: LICENSE.txt
Classifier: Development Status :: 4 - Beta
Classifier: Programming Language :: Python
Classifier: Programming Language :: Python :: 3.7
Classifier: Programming Language :: Python :: 3.8
Classifier: Programming Language :: Python :: 3.9
Classifier: Programming Language :: Python :: 3.10
Classifier: Programming Language :: Python :: 3.11
Classifier: Programming Language :: Python :: Implementation :: CPython
Classifier: Programming Language :: Python :: Implementation :: PyPy
Requires-Python: >=3.7
Requires-Dist: loguru
Requires-Dist: playwright
Requires-Dist: python-dotenv
Requires-Dist: pywin32
